{
    "adguard": {
        "cargoLocks": null,
        "date": null,
        "extract": null,
        "name": "adguard",
        "passthru": null,
        "pinned": false,
        "src": {
            "arch": null,
            "finalImageName": null,
            "finalImageTag": null,
            "imageDigest": "sha256:e8739116749fb37d7c66b0f47207fd0844816cefcbd35100b06bca8df23adac9",
            "imageName": "adguard/adguardhome",
            "imageTag": "v0.108.0-b.61",
            "os": null,
            "sha256": "sha256-Dn/YBp4gepQYQeuWyhdJt7aa32gTBz5zWZKKD5DaHN4=",
            "tlsVerify": null
        },
        "version": "v0.108.0-b.61"
    },
    "bazarr": {
        "cargoLocks": null,
        "date": null,
        "extract": null,
        "name": "bazarr",
        "passthru": null,
        "pinned": false,
        "src": {
            "arch": null,
            "finalImageName": null,
            "finalImageTag": null,
            "imageDigest": "sha256:ac9fe56bee9133bcb9e27fe48faaf83c57b83d75bacc277d9b2619136632b1fe",
            "imageName": "linuxserver/bazarr",
            "imageTag": "1.5.1",
            "os": null,
            "sha256": "sha256-xSr7YKWSHB1Ma7o1eEInGF4yD8g097kqRUUCNVxVCvc=",
            "tlsVerify": null
        },
        "version": "1.5.1"
    },
    "caddy": {
        "cargoLocks": null,
        "date": null,
        "extract": null,
        "name": "caddy",
        "passthru": null,
        "pinned": false,
        "src": {
            "arch": null,
            "finalImageName": null,
            "finalImageTag": null,
            "imageDigest": "sha256:2c136eb7e4daa97deed8738aab21994ea88dc0ced06aa44e30a949ba3d60e213",
            "imageName": "library/caddy",
            "imageTag": "2.9.1",
            "os": null,
            "sha256": "sha256-BjLwNrXPZFwZs7Fau/pxhUPSImBT8ms+nUVBs1PO4H8=",
            "tlsVerify": null
        },
        "version": "2.9.1"
    },
    "jellyfin": {
        "cargoLocks": null,
        "date": null,
        "extract": null,
        "name": "jellyfin",
        "passthru": null,
        "pinned": false,
        "src": {
            "arch": null,
            "finalImageName": null,
            "finalImageTag": null,
            "imageDigest": "sha256:e7d86520e47c75ea808fff9cfddb74e11551d410980337e7c5e5d191bc023a5a",
            "imageName": "jellyfin/jellyfin",
            "imageTag": "2025010605",
            "os": null,
            "sha256": "sha256-+Azuv0RHwa1BiLOyA3Dcdgk17e0Mn0Uky8YkuIOxb9A=",
            "tlsVerify": null
        },
        "version": "2025010605"
    },
    "prowlarr": {
        "cargoLocks": null,
        "date": null,
        "extract": null,
        "name": "prowlarr",
        "passthru": null,
        "pinned": false,
        "src": {
            "arch": null,
            "finalImageName": null,
            "finalImageTag": null,
            "imageDigest": "sha256:1f235ff7a178444398a9a431a4e65704d22f83a348192dececf75811212c9217",
            "imageName": "linuxserver/prowlarr",
            "imageTag": "1.29.2",
            "os": null,
            "sha256": "sha256-RovkWU9rEQmhDAT2p5QtGjEoDuWQVcPabux82jG+Xfs=",
            "tlsVerify": null
        },
        "version": "1.29.2"
    },
    "qbittorrent": {
        "cargoLocks": null,
        "date": null,
        "extract": null,
        "name": "qbittorrent",
        "passthru": null,
        "pinned": false,
        "src": {
            "arch": null,
            "finalImageName": null,
            "finalImageTag": null,
            "imageDigest": "sha256:fc98c8af048936d0070dc5e5992feab08664f8a61a860d91be02f782f8721485",
            "imageName": "linuxserver/qbittorrent",
            "imageTag": "20.04.1",
            "os": null,
            "sha256": "sha256-GZAC1cA7pShhKQB92d8JMbsUUYICplel+Mp2GqkFH/w=",
            "tlsVerify": null
        },
        "version": "20.04.1"
    },
    "radarr": {
        "cargoLocks": null,
        "date": null,
        "extract": null,
        "name": "radarr",
        "passthru": null,
        "pinned": false,
        "src": {
            "arch": null,
            "finalImageName": null,
            "finalImageTag": null,
            "imageDigest": "sha256:e633fc93b9e2cea959853d27c6acc1d0b2d1ed7db4a800f6f46fe5b217f13102",
            "imageName": "linuxserver/radarr",
            "imageTag": "5.17.2",
            "os": null,
            "sha256": "sha256-s7LVbtOUeDcfamvuRumWOvLGx8aR4M4PqNN8S8YqLvA=",
            "tlsVerify": null
        },
        "version": "5.17.2"
    },
    "sonarr": {
        "cargoLocks": null,
        "date": null,
        "extract": null,
        "name": "sonarr",
        "passthru": null,
        "pinned": false,
        "src": {
            "arch": null,
            "finalImageName": null,
            "finalImageTag": null,
            "imageDigest": "sha256:23f6911b2b81cb69aa03166b53c15081d5c3a5ed58f5b183c5900c2d8fc9759a",
            "imageName": "linuxserver/sonarr",
            "imageTag": "4.0.12",
            "os": null,
            "sha256": "sha256-BRAMd1mjH622xY5/w/xR1D0GnS/TUSrebZVo9paCKmo=",
            "tlsVerify": null
        },
        "version": "4.0.12"
    },
    "tor-privoxy": {
        "cargoLocks": null,
        "date": null,
        "extract": null,
        "name": "tor-privoxy",
        "passthru": null,
        "pinned": false,
        "src": {
            "arch": null,
            "finalImageName": null,
            "finalImageTag": null,
            "imageDigest": "sha256:7688b62223e1107adcda1418c2f9f95f9173abec7118431d776a0793135844f0",
            "imageName": "dockage/tor-privoxy",
            "imageTag": "latest",
            "os": null,
            "sha256": "sha256-pWk0Ci7gSSfzUaY2bOtOaMlFnBjO0gBtwIU7nuq8ZMQ=",
            "tlsVerify": null
        },
        "version": "latest"
    }
}